<?xml version="1.0"?>
<opencv_storage>
<stage15>
  <maxWeakCount>100</maxWeakCount>
  <stageThreshold>-1.7771351337432861e+00</stageThreshold>
  <weakClassifiers>
    <_>
      <internalNodes>
        0 -1 4423 -706742337 -285226065 -804782661 -311046914 -114294857
        -2163287 -92295233 -1984958481</internalNodes>
      <leafValues>
        -3.7235137820243835e-01 3.6700028926134109e-02</leafValues></_>
    <_>
      <internalNodes>
        0 -1 35 -540279885 -137252991 -1288441737 1441210801 -1665078789
        -80310537 -1377021955 1475572471</internalNodes>
      <leafValues>
        -1.3258300721645355e-01 1.5970440208911896e-01</leafValues></_>
    <_>
      <internalNodes>
        0 -1 2685 -34605150 -819301726 -168083726 -1079528966 586521999
        1288478477 -1214778382 -167805185</internalNodes>
      <leafValues>
        -9.6572645008563995e-02 1.8102978169918060e-01</leafValues></_>
    <_>
      <internalNodes>
        0 -1 705 -335563849 -97274537 -95213645 838069146 1204889332
        1072893325 -404664730 -512231517</internalNodes>
      <leafValues>
        -9.2221386730670929e-02 1.7008481919765472e-01</leafValues></_>
    <_>
      <internalNodes>
        0 -1 832 -406143557 -101650512 -1347146753 -832784 259952573
        -34529319 267332575 -166701</internalNodes>
      <leafValues>
        -6.8612076342105865e-02 2.1954578161239624e-01</leafValues></_>
    <_>
      <internalNodes>
        0 -1 3210 -856697374 -358178910 -1497520 1945872114 -1885877809
        206433765 1676669082 -941623830</internalNodes>
      <leafValues>
        -8.4565408527851105e-02 1.6406761109828949e-01</leafValues></_>
    <_>
      <internalNodes>
        0 -1 9558 -903889223 -361712014 -1094938735 -311421022
        1960296330 -294678796 -1104093289 -1979254893</internalNodes>
      <leafValues>
        -9.7528077661991119e-02 1.3619278371334076e-01</leafValues></_>
    <_>
      <internalNodes>
        0 -1 4374 -1150239819 -1409312015 -1208739063 1032139505
        -671335602 -67871313 2146895293 -286528381</internalNodes>
      <leafValues>
        -5.9435043483972549e-02 1.7842684686183929e-01</leafValues></_>
    <_>
      <internalNodes>
        0 -1 2275 1282768766 976264695 1073446683 1066941187 1186997156
        -1628907676 1689627646 -1162847132</internalNodes>
      <leafValues>
        -9.1925360262393951e-02 1.3674260675907135e-01</leafValues></_>
    <_>
      <internalNodes>
        0 -1 1971 -957611300 -982780439 -1042963974 1285942249
        1958238060 -270344203 1907001056 -448428614</internalNodes>
      <leafValues>
        -1.4510796964168549e-01 8.6413376033306122e-02</leafValues></_>
    <_>
      <internalNodes>
        0 -1 9175 -60111660 2107161901 -73646275 767536625 535493244
        -1099403393 1006384852 -1081922558</internalNodes>
      <leafValues>
        -1.0258919000625610e-01 1.1852304637432098e-01</leafValues></_>
    <_>
      <internalNodes>
        0 -1 171 1460312976 762412820 -872542321 909423602 1355685836
        1939244774 -1495462676 2144293779</internalNodes>
      <leafValues>
        -1.1771092563867569e-01 1.0328412055969238e-01</leafValues></_>
    <_>
      <internalNodes>
        0 -1 519 -958926889 -180391189 -1113690141 -1225531402 -51143726
        -145255153 -346817005 -100452489</internalNodes>
      <leafValues>
        -8.3591967821121216e-02 1.5879882872104645e-01</leafValues></_>
    <_>
      <internalNodes>
        0 -1 5393 -531186660 904291767 -16794249 -1275166758 209582005
        -285470753 2143239144 -1545109214</internalNodes>
      <leafValues>
        -1.0870534181594849e-01 1.1434304714202881e-01</leafValues></_>
    <_>
      <internalNodes>
        0 -1 7309 1746200884 33996503 -1516246292 -1817535745 1813841273
        -1403080193 430795071 -2143518460</internalNodes>
      <leafValues>
        -1.5266229212284088e-01 7.9523265361785889e-02</leafValues></_>
    <_>
      <internalNodes>
        0 -1 1542 553116652 1484450728 -1837675712 2144611426 1289160069
        1157773414 1378694171 209022992</internalNodes>
      <leafValues>
        -1.7757059633731842e-01 6.5819866955280304e-02</leafValues></_>
    <_>
      <internalNodes>
        0 -1 6495 1583149045 -134430849 -42022482 -1283836065 -793991323
        -1080165643 -939676171 355477480</internalNodes>
      <leafValues>
        -1.6081608831882477e-01 7.1671932935714722e-02</leafValues></_>
    <_>
      <internalNodes>
        0 -1 9943 -690498541 -178540705 -353096974 1929379539 -27288242
        1333558827 -16808264 -218370177</internalNodes>
      <leafValues>
        -7.7186547219753265e-02 1.5335115790367126e-01</leafValues></_>
    <_>
      <internalNodes>
        0 -1 761 -1242040809 -211550281 -270338725 -1289538014
        -987367593 -92799945 -1087906017 -362549898</internalNodes>
      <leafValues>
        -6.8611599504947662e-02 1.6252125799655914e-01</leafValues></_>
    <_>
      <internalNodes>
        0 -1 7352 116696372 -1225490594 -370452836 -1115756782 343759744
        1054733311 -1006692480 -1510691316</internalNodes>
      <leafValues>
        -1.7315064370632172e-01 6.4072072505950928e-02</leafValues></_>
    <_>
      <internalNodes>
        0 -1 12 1112393683 1564814385 1019187541 -1346740446 -588413441
        1849355431 -1065399045 1226746867</internalNodes>
      <leafValues>
        -7.9580456018447876e-02 1.3963425159454346e-01</leafValues></_>
    <_>
      <internalNodes>
        0 -1 261 -814768233 1441426799 -1458184030 -1095092126
        -968934539 2006563471 1736799376 -254413130</internalNodes>
      <leafValues>
        -1.2492731958627701e-01 9.0851239860057831e-02</leafValues></_>
    <_>
      <internalNodes>
        0 -1 1170 1551621331 -542413978 1672158833 -114880970 -809502936
        -118196225 -1805967974 -24527925</internalNodes>
      <leafValues>
        -5.6511737406253815e-02 1.9521814584732056e-01</leafValues></_>
    <_>
      <internalNodes>
        0 -1 7424 -849799868 857671583 -1647333522 801975231 -214161544
        1979473658 1450221094 -1238864093</internalNodes>
      <leafValues>
        -1.3352672755718231e-01 8.7203323841094971e-02</leafValues></_>
    <_>
      <internalNodes>
        0 -1 9638 1935822640 2049597228 248540947 -1092431304 1936195902
        735330401 1551683934 673253488</internalNodes>
      <leafValues>
        -1.9599217176437378e-01 5.7537242770195007e-02</leafValues></_>
    <_>
      <internalNodes>
        0 -1 596 -295809246 1333321514 913258962 -1747164754 1189354447
        527225710 2012105724 2045146999</internalNodes>
      <leafValues>
        -1.1741300672292709e-01 9.6320465207099915e-02</leafValues></_>
    <_>
      <internalNodes>
        0 -1 4766 1141865323 -2000312604 928968698 294189822 -638460685
        -1359090755 1740595411 -90205237</internalNodes>
      <leafValues>
        -7.9208932816982269e-02 1.4512351155281067e-01</leafValues></_>
    <_>
      <internalNodes>
        0 -1 3109 10232224 520199280 -85964820 2123128481 1085759925
        1749131155 -601400911 606868368</internalNodes>
      <leafValues>
        -2.1740716695785522e-01 5.4337307810783386e-02</leafValues></_>
    <_>
      <internalNodes>
        0 -1 6606 -607256913 -196242191 640472511 -119039945 745358555
        -739835917 -1682180612 -656210129</internalNodes>
      <leafValues>
        -6.5755382180213928e-02 1.9075019657611847e-01</leafValues></_>
    <_>
      <internalNodes>
        0 -1 4933 -909600575 574940007 802757630 -1374636403 2040275685
        998620987 -542820505 63513159</internalNodes>
      <leafValues>
        -1.3272726535797119e-01 8.3866141736507416e-02</leafValues></_>
    <_>
      <internalNodes>
        0 -1 3468 1434245176 -1386727897 284704634 -1591673305
        1509283281 -1725125116 -941234698 753800448</internalNodes>
      <leafValues>
        -1.6584667563438416e-01 6.5777570009231567e-02</leafValues></_>
    <_>
      <internalNodes>
        0 -1 553 -823841937 325281601 1700034824 -762916885 720392516
        776362328 288701468 1061451672</internalNodes>
      <leafValues>
        -1.2451767176389694e-01 8.9814506471157074e-02</leafValues></_>
    <_>
      <internalNodes>
        0 -1 147 266831967 -1691319309 -1510824106 1598942368 -993262081
        -292809362 1818227195 -1455447049</internalNodes>
      <leafValues>
        -8.1102982163429260e-02 1.4172740280628204e-01</leafValues></_>
    <_>
      <internalNodes>
        0 -1 1360 -3674585 2075819946 -317215149 -139723096 1308510681
        -1115234357 1442641082 -370147409</internalNodes>
      <leafValues>
        -5.3374391049146652e-02 2.1161513030529022e-01</leafValues></_>
    <_>
      <internalNodes>
        0 -1 7620 -323178891 1031200703 1073479386 -475246 1549760461
        -543377537 -1359894801 -1344312146</internalNodes>
      <leafValues>
        -7.5361818075180054e-02 1.4782561361789703e-01</leafValues></_>
    <_>
      <internalNodes>
        0 -1 1096 -574644349 1873018763 637251568 -1711607826
        -1957758515 -592838887 -1241901328 -506992674</internalNodes>
      <leafValues>
        -8.0734714865684509e-02 1.3778790831565857e-01</leafValues></_>
    <_>
      <internalNodes>
        0 -1 6325 3933220 14704625 1053764064 610582472 974416902
        146190679 889869124 81818880</internalNodes>
      <leafValues>
        -4.1534572839736938e-01 2.6805620640516281e-02</leafValues></_>
    <_>
      <internalNodes>
        0 -1 3820 887262848 1349155649 -1420295227 79763928 284705337
        -12419239 -874257059 1021623956</internalNodes>
      <leafValues>
        -1.8009918928146362e-01 6.0111243277788162e-02</leafValues></_>
    <_>
      <internalNodes>
        0 -1 3128 -246799824 6029376 1529725069 710715057 -144949632
        -212923294 -1896278971 14238805</internalNodes>
      <leafValues>
        -1.7698557674884796e-01 6.4564585685729980e-02</leafValues></_>
    <_>
      <internalNodes>
        0 -1 1504 1156768610 1733190471 1073409532 -1196500854
        1616858342 -1637908689 1090440428 -258569142</internalNodes>
      <leafValues>
        -1.0391969233751297e-01 1.0285423696041107e-01</leafValues></_>
    <_>
      <internalNodes>
        0 -1 630 163309334 688107333 659679289 -276566687 -2107262730
        -17545211 -1913411145 940928130</internalNodes>
      <leafValues>
        -1.1678458750247955e-01 9.1616980731487274e-02</leafValues></_>
    <_>
      <internalNodes>
        0 -1 9798 102770980 1691151157 194896830 36973488 627341077
        1216703481 882976032 1051924</internalNodes>
      <leafValues>
        -4.5299237966537476e-01 2.5165036320686340e-02</leafValues></_>
    <_>
      <internalNodes>
        0 -1 1560 -86265 2134769503 933671722 308737962 -1929982004
        -1355284649 -398356 -457038354</internalNodes>
      <leafValues>
        -8.3280913531780243e-02 1.3059113919734955e-01</leafValues></_>
    <_>
      <internalNodes>
        0 -1 1301 -555297897 300822501 1319898766 2107881383 1358693620
        -1124634719 -774401718 1148712382</internalNodes>
      <leafValues>
        -9.8301626741886139e-02 1.1309376358985901e-01</leafValues></_>
    <_>
      <internalNodes>
        0 -1 1621 203434532 -1801155168 -390035279 109842641 59580776
        -1478190809 -1402988547 147324932</internalNodes>
      <leafValues>
        -2.7287393808364868e-01 3.9412420243024826e-02</leafValues></_>
    <_>
      <internalNodes>
        0 -1 893 -907281933 -11244107 166936120 2110651283 -857743912
        -30683057 1039387872 -372251953</internalNodes>
      <leafValues>
        -5.6207396090030670e-02 2.0185518264770508e-01</leafValues></_>
    <_>
      <internalNodes>
        0 -1 4916 748697064 244649416 -946002234 682192833 1395947397
        557409924 1003366959 -2069056111</internalNodes>
      <leafValues>
        -1.5837067365646362e-01 6.8772472441196442e-02</leafValues></_>
    <_>
      <internalNodes>
        0 -1 3613 1585390514 342911010 -1055677446 905554466 302342884
        79980732 1139905026 409306855</internalNodes>
      <leafValues>
        -1.3214688003063202e-01 8.4330461919307709e-02</leafValues></_>
    <_>
      <internalNodes>
        0 -1 7999 143663120 -1790166668 420772315 -1205063108 836701054
        227401399 122491213 203424816</internalNodes>
      <leafValues>
        -4.6398246288299561e-01 2.3807603865861893e-02</leafValues></_>
    <_>
      <internalNodes>
        0 -1 9923 -4209535 1988935215 -1866471760 1347640442 -178792308
        255917909 1995439698 870573055</internalNodes>
      <leafValues>
        -8.8187597692012787e-02 1.2609870731830597e-01</leafValues></_>
    <_>
      <internalNodes>
        0 -1 3994 -338755839 -483532830 -1091000734 464797600 410947469
        1290088415 -403196202 -172763695</internalNodes>
      <leafValues>
        -9.1879852116107941e-02 1.2104901671409607e-01</leafValues></_>
    <_>
      <internalNodes>
        0 -1 6360 -472401953 -1147212803 -32663751 1192343415
        -1258630759 -1090536091 -1644702134 -935621193</internalNodes>
      <leafValues>
        -6.2707059085369110e-02 1.8345685303211212e-01</leafValues></_>
    <_>
      <internalNodes>
        0 -1 2889 82302370 -1206739411 1404915262 492859071 1155233524
        -1699312974 1395887193 -928726236</internalNodes>
      <leafValues>
        -1.2013442814350128e-01 9.7587198019027710e-02</leafValues></_>
    <_>
      <internalNodes>
        0 -1 5223 76307968 680538364 951460737 -1471481201 819477281
        1231008967 -411811386 1344554764</internalNodes>
      <leafValues>
        -2.4633799493312836e-01 4.4404741376638412e-02</leafValues></_>
    <_>
      <internalNodes>
        0 -1 1613 -1629118766 -570574158 314430973 518836643 1541191539
        1042820400 1869992182 2062931683</internalNodes>
      <leafValues>
        -9.1619297862052917e-02 1.2100929021835327e-01</leafValues></_>
    <_>
      <internalNodes>
        0 -1 7366 670303516 299266839 1317518300 1060767586 1240022164
        1287683401 -1924375816 -1586126834</internalNodes>
      <leafValues>
        -1.4082106947898865e-01 7.9020328819751740e-02</leafValues></_>
    <_>
      <internalNodes>
        0 -1 1420 1616901907 888990790 -1588327392 1682187515 834978551
        1034418409 1670017564 1625717278</internalNodes>
      <leafValues>
        -1.3626772165298462e-01 8.2912608981132507e-02</leafValues></_>
    <_>
      <internalNodes>
        0 -1 700 -1888765209 -1974468891 -286953731 -483248351
        -1796151486 1599143918 -1216909136 1062167169</internalNodes>
      <leafValues>
        -1.0082650929689407e-01 1.1390490829944611e-01</leafValues></_>
    <_>
      <internalNodes>
        0 -1 5280 584424518 -692791354 930293414 668400527 -1335087933
        1980185191 -246659 1859461959</internalNodes>
      <leafValues>
        -1.2833379209041595e-01 8.8095210492610931e-02</leafValues></_>
    <_>
      <internalNodes>
        0 -1 7667 652482220 -1436434538 -1565440100 -1288515934
        -2131329610 -627526817 -1869196039 -860679126</internalNodes>
      <leafValues>
        -1.4336547255516052e-01 8.0185249447822571e-02</leafValues></_>
    <_>
      <internalNodes>
        0 -1 272 1034608752 136489564 565744574 -860588650 358698177
        -1847833765 -1930979904 74487700</internalNodes>
      <leafValues>
        -1.8482816219329834e-01 6.6787481307983398e-02</leafValues></_>
    <_>
      <internalNodes>
        0 -1 1836 1575864613 -546976075 367835586 1509612159 -1669470471
        224356190 -1334338706 -113351249</internalNodes>
      <leafValues>
        -7.3373891413211823e-02 1.5951780974864960e-01</leafValues></_>
    <_>
      <internalNodes>
        0 -1 352 644138512 -1722417178 989136660 1379101750 -241100360
        -1947107699 1972584618 753336320</internalNodes>
      <leafValues>
        -1.4635169506072998e-01 7.5954332947731018e-02</leafValues></_>
    <_>
      <internalNodes>
        0 -1 9167 612237344 1306267437 -745763196 578179878 -77994416
        1826966012 1987879512 303047814</internalNodes>
      <leafValues>
        -2.1885573863983154e-01 5.0279948860406876e-02</leafValues></_>
    <_>
      <internalNodes>
        0 -1 7 435229744 -107061787 2055490267 429435008 545170942
        -29739827 -1491811335 -2011594623</internalNodes>
      <leafValues>
        -1.5372435748577118e-01 7.0404648780822754e-02</leafValues></_>
    <_>
      <internalNodes>
        0 -1 9033 -479740289 833132479 -844958409 -1498677570 -413878539
        -1287850049 -279094049 -611063601</internalNodes>
      <leafValues>
        -5.3327579051256180e-02 2.0336729288101196e-01</leafValues></_>
    <_>
      <internalNodes>
        0 -1 9415 414712832 46536482 -361420182 546352786 -219081468
        232790887 66911780 538981636</internalNodes>
      <leafValues>
        -3.6206313967704773e-01 3.0358042567968369e-02</leafValues></_>
    <_>
      <internalNodes>
        0 -1 531 -807997517 256732543 66528417 1007788274 -175507992
        -1081372753 -872960262 2094880115</internalNodes>
      <leafValues>
        -9.1050460934638977e-02 1.2383223325014114e-01</leafValues></_>
    <_>
      <internalNodes>
        0 -1 1035 -946896961 -1028277633 -8601777 255974147 1241595796
        -251876230 1957817407 -480779193</internalNodes>
      <leafValues>
        -7.8189767897129059e-02 1.4590509235858917e-01</leafValues></_>
    <_>
      <internalNodes>
        0 -1 7148 786706212 1313619682 1455828128 884617208 779476711
        1291307037 603445126 -1815386420</internalNodes>
      <leafValues>
        -1.3840772211551666e-01 8.5228160023689270e-02</leafValues></_>
    <_>
      <internalNodes>
        0 -1 2499 1755838725 -2026016027 -1039024264 90054480 2095029546
        -1351421969 -88802393 221281240</internalNodes>
      <leafValues>
        -1.2212723493576050e-01 9.5750197768211365e-02</leafValues></_>
    <_>
      <internalNodes>
        0 -1 8842 -1907377923 -1961755753 -874058130 153271715 928973878
        489877131 553156307 172574468</internalNodes>
      <leafValues>
        -1.2184852361679077e-01 9.6668429672718048e-02</leafValues></_>
    <_>
      <internalNodes>
        0 -1 4234 -512780028 290906571 -1755371878 1006272298 1174146020
        1023344313 -503601448 -802031762</internalNodes>
      <leafValues>
        -1.1459612846374512e-01 1.0422928631305695e-01</leafValues></_>
    <_>
      <internalNodes>
        0 -1 9332 4719876 46102287 -1229022686 1255042602 820143620
        905738103 2024174608 589308978</internalNodes>
      <leafValues>
        -2.7667099237442017e-01 4.1455477476119995e-02</leafValues></_>
    <_>
      <internalNodes>
        0 -1 767 2144755185 1756894510 -959114741 968534138 -2035060283
        1239542195 -1798855609 1660126343</internalNodes>
      <leafValues>
        -1.2494930624961853e-01 8.8233046233654022e-02</leafValues></_>
    <_>
      <internalNodes>
        0 -1 2965 -272886499 -724107969 -84141129 1476321262 -302727736
        2144726911 -148275 -135586134</internalNodes>
      <leafValues>
        -7.0788688957691193e-02 1.5985031425952911e-01</leafValues></_>
    <_>
      <internalNodes>
        0 -1 5985 542376708 741369917 -1145428116 78786416 1215106420
        106331983 544474436 5244736</internalNodes>
      <leafValues>
        -5.2404344081878662e-01 2.1844271570444107e-02</leafValues></_>
    <_>
      <internalNodes>
        0 -1 1043 -838883678 -615793616 1878947317 1944567698 1037948220
        -826757710 692372923 -10117022</internalNodes>
      <leafValues>
        -7.5639791786670685e-02 1.5160714089870453e-01</leafValues></_>
    <_>
      <internalNodes>
        0 -1 9664 202648868 241188629 -1077734216 872724080 363613221
        2002275071 650387588 2098208</internalNodes>
      <leafValues>
        -3.9193817973136902e-01 3.0151497572660446e-02</leafValues></_>
    <_>
      <internalNodes>
        0 -1 8200 -135350291 1924130783 -454189502 1925595114 -269139993
        1509851101 -177330780 -134283105</internalNodes>
      <leafValues>
        -7.1700856089591980e-02 1.6481606662273407e-01</leafValues></_>
    <_>
      <internalNodes>
        0 -1 1762 -819150893 1200545331 -1134570762 -1868856096
        -362106993 -1425809588 1278473715 -573182757</internalNodes>
      <leafValues>
        -7.1019738912582397e-02 1.6389775276184082e-01</leafValues></_>
    <_>
      <internalNodes>
        0 -1 1914 174506866 330755429 -1344582651 -2132697118
        -1722256123 137689791 712396234 1138752759</internalNodes>
      <leafValues>
        -1.2534666061401367e-01 9.6640244126319885e-02</leafValues></_>
    <_>
      <internalNodes>
        0 -1 6375 -588514311 -1611061315 -319144841 -243292420
        2122030969 -621903906 -135446898 -2017747685</internalNodes>
      <leafValues>
        -6.2074519693851471e-02 1.8441686034202576e-01</leafValues></_>
    <_>
      <internalNodes>
        0 -1 6678 -1054927708 544929766 -1390830321 1682484087
        -764986780 688278188 1591230432 178382615</internalNodes>
      <leafValues>
        -1.6268701851367950e-01 6.9541171193122864e-02</leafValues></_>
    <_>
      <internalNodes>
        0 -1 4334 -69681641 1525080943 -71393881 -707066704 -1295762000
        -2533815 327081279 -424775678</internalNodes>
      <leafValues>
        -8.8743761181831360e-02 1.3142842054367065e-01</leafValues></_>
    <_>
      <internalNodes>
        0 -1 7572 640167428 351834011 381302448 12061442 399795733
        267697999 1634065572 569115924</internalNodes>
      <leafValues>
        -2.8501608967781067e-01 3.9368871599435806e-02</leafValues></_>
    <_>
      <internalNodes>
        0 -1 6686 -303534928 500823857 1889425910 933001716 -2049625140
        16320307 -223541261 -1997722466</internalNodes>
      <leafValues>
        -1.2175455689430237e-01 9.3276038765907288e-02</leafValues></_>
    <_>
      <internalNodes>
        0 -1 3637 -340989177 1520713527 1859874801 -1238057870
        1724898772 -545562769 -1293570372 -206080012</internalNodes>
      <leafValues>
        -9.1006092727184296e-02 1.2437519431114197e-01</leafValues></_>
    <_>
      <internalNodes>
        0 -1 8755 77736964 983711271 -1680288424 146980506 1496323557
        282513991 1960119888 10759232</internalNodes>
      <leafValues>
        -3.4234812855720520e-01 3.3827647566795349e-02</leafValues></_>
    <_>
      <internalNodes>
        0 -1 5462 -979183044 -1698955417 -1980952893 288030579
        -983474708 -846706852 -185640583 -1805128006</internalNodes>
      <leafValues>
        -9.4783641397953033e-02 1.2012117356061935e-01</leafValues></_>
    <_>
      <internalNodes>
        0 -1 8726 -2143914667 -1485589521 -1453333210 -1125358655
        -57328147 627518199 -698106196 -2080744186</internalNodes>
      <leafValues>
        -1.1152797937393188e-01 1.0271798819303513e-01</leafValues></_>
    <_>
      <internalNodes>
        0 -1 1998 413551916 414052516 1541463056 -1777839656 1219049381
        -521938235 938902964 944849944</internalNodes>
      <leafValues>
        -1.9239798188209534e-01 5.9886183589696884e-02</leafValues></_>
    <_>
      <internalNodes>
        0 -1 9996 -35195165 -397295707 -109281417 1782889066 1582839141
        251493599 972916371 -321665294</internalNodes>
      <leafValues>
        -7.2472430765628815e-02 1.5852457284927368e-01</leafValues></_>
    <_>
      <internalNodes>
        0 -1 6263 69087906 -1236010203 1725728912 664859323 807168077
        -1322132121 -1493321653 1120474981</internalNodes>
      <leafValues>
        -1.4416238665580750e-01 7.8787691891193390e-02</leafValues></_>
    <_>
      <internalNodes>
        0 -1 6185 -845430875 1534031781 -234985964 -1160090812
        1316861343 1328543591 2147231188 -151787971</internalNodes>
      <leafValues>
        -8.6285568773746490e-02 1.3499380648136139e-01</leafValues></_>
    <_>
      <internalNodes>
        0 -1 898 125967813 -890029689 -26531772 919341026 -2071621307
        450182104 231244197 1003808560</internalNodes>
      <leafValues>
        -1.4514191448688507e-01 8.4640100598335266e-02</leafValues></_>
    <_>
      <internalNodes>
        0 -1 6609 -211436899 -252856174 2045622015 -1751777677
        1903126519 -87699776 -970523973 -1343772401</internalNodes>
      <leafValues>
        -6.3720397651195526e-02 1.8604665994644165e-01</leafValues></_>
    <_>
      <internalNodes>
        0 -1 7863 1996760850 -300532003 150838067 903621183 -604369108
        -1900217196 1963627532 -2059364848</internalNodes>
      <leafValues>
        -1.8048217892646790e-01 6.3909180462360382e-02</leafValues></_>
    <_>
      <internalNodes>
        0 -1 4948 673220133 1196211068 -846221554 -857192784 933225814
        1044184942 292489830 96167332</internalNodes>
      <leafValues>
        -1.7050698399543762e-01 6.7981190979480743e-02</leafValues></_>
    <_>
      <internalNodes>
        0 -1 4898 1624941000 345811388 1173043767 87852213 -1790614115
        -1763348865 846290925 -1681267921</internalNodes>
      <leafValues>
        -9.0555399656295776e-02 1.2978434562683105e-01</leafValues></_></weakClassifiers></stage15>
</opencv_storage>
